auto_diff/__init__.py
auto_diff/numpy_masking.py
auto_diff/sparse_numpy_masking.py
auto_diff/sparsevecvalder.py
auto_diff/sparsevecvalder_funcs_and_ufuncs.py
auto_diff/test_auto_diff_on_dae.py
auto_diff/true_np.py
auto_diff/vecvalder.py
auto_diff/vecvalder_funcs_and_ufuncs.py
auto_diff-0.4.1.dist-info/LICENSE
auto_diff-0.4.1.dist-info/METADATA
auto_diff-0.4.1.dist-info/WHEEL
auto_diff-0.4.1.dist-info/top_level.txt
auto_diff-0.4.1.dist-info/RECORD
