Metadata-Version: 2.1
Name: auto-diff
Version: 0.4.1
Summary: An automatic differentiation library for Python+NumPy.
Home-page: https://github.com/PTNobel/autodiff
Author: Parth Nobel
Author-email: parthnobel@berkeley.edu
Classifier: Programming Language :: Python :: 3
Classifier: License :: OSI Approved
Classifier: Operating System :: OS Independent
Requires-Python: >=3.8
License-File: LICENSE
Requires-Dist: numpy (>=1.17)
